{
    "Title": "The Element of Crime",
    "Year": "1984",
    "Rated": "Not Rated",
    "Released": "14 May 1984",
    "Runtime": "104 min",
    "Genre": "Crime, Drama, Thriller",
    "Director": "Lars von Trier",
    "Writer": "Lars von Trier, Niels Vørsel, William Quarshie",
    "Actors": "Michael Elphick, Esmond Knight, Me Me Lai",
    "Plot": "A cop in a dystopian Europe investigates a serial killings suspect using controversial methods written by his now disgraced former mentor.",
    "Language": "English, Arabic, German",
    "Country": "Denmark",
    "Awards": "12 wins & 3 nominations total",
    "Poster": "https://m.media-amazon.com/images/M/MV5BNWZhMDE0MzctZDllNC00ZmM1LWJhYTYtZmMwYjRmMDExMGVhXkEyXkFqcGc@._V1_SX300.jpg",
    "Ratings": [
        {
            "Source": "Internet Movie Database",
            "Value": "6.7/10"
        },
        {
            "Source": "Rotten Tomatoes",
            "Value": "83%"
        },
        {
            "Source": "Metacritic",
            "Value": "66/100"
        }
    ],
    "Metascore": "66",
    "imdbRating": "6.7",
    "imdbVotes": "11,606",
    "imdbID": "tt0087280",
    "Type": "movie",
    "DVD": "N/A",
    "BoxOffice": "N/A",
    "Production": "N/A",
    "Website": "N/A",
    "Response": "True"
}