{
    "Title": "Shakespeare in Love",
    "Year": "1998",
    "Plot": "History's greatest playwright is young, out of ideas and short of cash, but meets his ideal woman and is inspired to write one of his most famous plays.",
    "Language": "English",
    "Country": "United Kingdom, United States",
    "Rated": "R",
    "Runtime": "123 min",
    "Genre": "Comedy, Drama, History",
    "Director": "John Madden",
    "Actors": "Gwyneth Paltrow, Joseph Fiennes, Geoffrey Rush",
    "Awards": "Won 7 Oscars. 65 wins & 87 nominations total",
    "imdbID": "tt0138097",
    "imdbRating": "7.1",
    "BoxOffice": "$100,317,794",
    "TMDb_Rating": 6.843,
    "Poster_OMDb": "https://m.media-amazon.com/images/M/MV5BYmM3MTllNzYtN2MzNS00NWQwLTk0NTEtNjY1MmMwYjNkNTE5XkEyXkFqcGc@._V1_SX300.jpg",
    "Poster_TMDb": "https://image.tmdb.org/t/p/w500/zdW7jdzPi4J9KZR3TyY2jn3Xh5e.jpg",
    "Backdrops": [
        "https://image.tmdb.org/t/p/w500/2U5PTkyxjP8JJMIRCTAtqgzZ0kh.jpg",
        "https://image.tmdb.org/t/p/w500/fywJ6JdG3R6wRzR43yYQzOwW0T6.jpg",
        "https://image.tmdb.org/t/p/w500/sckmqSz9bCuCzyGO3zD4uWtL2BH.jpg",
        "https://image.tmdb.org/t/p/w500/b7sVklEPXerKEZFkn2XSQ8EL650.jpg"
    ],
    "Cast": [
        {
            "name": "Joseph Fiennes",
            "character": "Will Shakespeare",
            "profile_url": "https://image.tmdb.org/t/p/w500/sg5Z7nTvEPBqDKULvGXWzJRbnrU.jpg"
        },
        {
            "name": "Gwyneth Paltrow",
            "character": "Viola De Lesseps",
            "profile_url": "https://image.tmdb.org/t/p/w500/alLfgUJcSm2USn7BnG6Y7e9Znpr.jpg"
        },
        {
            "name": "Geoffrey Rush",
            "character": "Philip Henslowe",
            "profile_url": "https://image.tmdb.org/t/p/w500/4zQuC1j0p7HkJlfuT8aJoyZAgQm.jpg"
        },
        {
            "name": "Tom Wilkinson",
            "character": "Hugh Fennyman",
            "profile_url": "https://image.tmdb.org/t/p/w500/xSUohQDXuepOU2nSqtDj2us5RZo.jpg"
        },
        {
            "name": "Judi Dench",
            "character": "Queen Elizabeth",
            "profile_url": "https://image.tmdb.org/t/p/w500/cpna5VGvAxuKuC31xJPBKy9zbnv.jpg"
        },
        {
            "name": "Imelda Staunton",
            "character": "Nurse",
            "profile_url": "https://image.tmdb.org/t/p/w500/96LYLMnUOWZ4DFXEeQPItNsxzEP.jpg"
        },
        {
            "name": "Colin Firth",
            "character": "Lord Wessex",
            "profile_url": "https://image.tmdb.org/t/p/w500/4VBeYEUQbfhnivdkqInM36u5fda.jpg"
        },
        {
            "name": "Ben Affleck",
            "character": "Ned Alleyn",
            "profile_url": "https://image.tmdb.org/t/p/w500/aTcqu8cI4wMohU17xTdqmXKTGrw.jpg"
        },
        {
            "name": "Simon Callow",
            "character": "Tilney",
            "profile_url": "https://image.tmdb.org/t/p/w500/no6qlnMrWeUzSt1FjD2Vf9x992e.jpg"
        },
        {
            "name": "Steven Beard",
            "character": "Makepeace",
            "profile_url": null
        }
    ],
    "Directors": [
        "John Madden"
    ],
    "Trailer": "https://www.youtube.com/watch?v=_CxNF4eA6yw",
    "TMDb_ID": 1934
}