{
    "Title": "Justice League Dark: Apokolips War",
    "Year": "2020",
    "Plot": "A Sequel to Justice League Dark (2017) involving Jack Kirby's New Gods.",
    "Language": "English, Latin",
    "Country": "USA",
    "Rated": "R",
    "Runtime": "90 min",
    "Genre": "Animation, Action, Sci-Fi",
    "Director": "Matt Peters, Christina Sotta",
    "Actors": "Roger Cross, Rosario Dawson, Christopher Gorham, Camilla Luddington",
    "Awards": "N/A",
    "imdbID": "tt11079148",
    "imdbRating": "7.8",
    "BoxOffice": "N/A",
    "TMDb_Rating": 8.2,
    "Poster_OMDb": "https://m.media-amazon.com/images/M/MV5BZDNjMjE5YmUtOTUwOC00MjAyLWJmMzktZjlkMjQyYzNiNmU3XkEyXkFqcGdeQXVyNTA4NzExMDg@._V1_SX300.jpg",
    "Poster_TMDb": "https://image.tmdb.org/t/p/w500/c01Y4suApJ1Wic2xLmaq1QYcfoZ.jpg",
    "Backdrops": [
        "https://image.tmdb.org/t/p/w500/5FWDakqUBpVOtNUY9Id48iIszPk.jpg",
        "https://image.tmdb.org/t/p/w500/ygCVyAfj3xFu1lzma3QUftAttEb.jpg",
        "https://image.tmdb.org/t/p/w500/73Il8cPQw0yoW0UeaFJzpqE1bTh.jpg"
    ],
    "Cast": [
        {
            "name": "Matt Ryan",
            "character": "John Constantine (voice)",
            "profile_url": "https://image.tmdb.org/t/p/w500/qLx6rzn6MMcJtTals5Z7Mb6z4Y9.jpg"
        },
        {
            "name": "Jerry O'Connell",
            "character": "Clark Kent / Superman (voice)",
            "profile_url": "https://image.tmdb.org/t/p/w500/p2zcFeDIKUrPrbT5ODqoLifdN3Q.jpg"
        },
        {
            "name": "Taissa Farmiga",
            "character": "Rachel Roth / Raven (voice)",
            "profile_url": "https://image.tmdb.org/t/p/w500/kC2Movbs6uEF8DdDhvyHizQHuru.jpg"
        },
        {
            "name": "Jason O'Mara",
            "character": "Bruce Wayne / Batman (voice)",
            "profile_url": "https://image.tmdb.org/t/p/w500/9Cs9PD5pwUkFQPLmpp5e6wkFQoY.jpg"
        },
        {
            "name": "Rosario Dawson",
            "character": "Diana Prince / Wonder Woman (voice)",
            "profile_url": "https://image.tmdb.org/t/p/w500/1mm7JGHIUX3GRRGXEV9QCzsI0ao.jpg"
        },
        {
            "name": "Stuart Allan",
            "character": "Damian Wayne / Robin (voice)",
            "profile_url": "https://image.tmdb.org/t/p/w500/xCAGTIcgC7J6YCl2bviIADY8blp.jpg"
        },
        {
            "name": "Rebecca Romijn",
            "character": "Lois Lane (voice)",
            "profile_url": "https://image.tmdb.org/t/p/w500/5Jgmk7S3JxDUhdVLUFHUaJ42ovt.jpg"
        },
        {
            "name": "Rainn Wilson",
            "character": "Lex Luthor (voice)",
            "profile_url": "https://image.tmdb.org/t/p/w500/yRTElSeC3q9nBqBuleI6OODlDMS.jpg"
        },
        {
            "name": "Tony Todd",
            "character": "Darkseid (voice)",
            "profile_url": "https://image.tmdb.org/t/p/w500/5fZ0hKcRtFIFdgBFSL40LVFylfW.jpg"
        },
        {
            "name": "Shemar Moore",
            "character": "Victor Stone / Cyborg (voice)",
            "profile_url": "https://image.tmdb.org/t/p/w500/epkv0UiwrPfCK3c0sHemSMi2jeh.jpg"
        }
    ],
    "Directors": [
        "Matt Peters",
        "Christina Sotta"
    ],
    "Trailer": "https://www.youtube.com/watch?v=tnCkn5xD2jg",
    "TMDb_ID": 618344
}